Workbook

Sheet Dashboard
A1: Diggers Inn Restaurant & Pub — Inventory & Operations Dashboard
B2: Go to Inventory | E2: Daily Count | H2: Sales Log | K2: Purchases
B4: =B30 | E4: =C30 | H4: =D30 | K4: =E30
B7: =F30 | E7: =G30 | H7: =H30 | K7: =I30
A11: Low Stock List | F11: Top Selling Products | J11: 7-Day Sales Data
A12: Item | B12: Current Stock | C12: Reorder Level | D12: Status | F12: Item | G12: Qty Sold | J12: Date | K12: Sales Total
A13: =FILTER({'Inventory Master'!A3:A300,'Inventory Master'!J3:J300,'Inventory Master'!K3:K300,'Inventory Master'!L3:L300},'Inventory Master'!L3:L300="REORDER") | F13: =QUERY({'Sales Log'!C3:C2000,'Sales Log'!D3:D2000},"select Col1,sum(Col2) where Col1 is not null group by Col1 order by sum(Col2) desc limit 5 label Col1 'Item', sum(Col2) 'Qty Sold'",0) | J13: =QUERY({'Sales Log'!A3:A2000,'Sales Log'!F3:F2000},"select Col1,sum(Col2) where Col1 is not null group by Col1 order by Col1 desc limit 7 label Col1 'Date', sum(Col2) 'Sales Total'",0)
A27: Tip: staff should only type in cream-coloured cells. Grey cells calculate automatically.
B30: =SUMIFS('Sales Log'!$F:$F,'Sales Log'!$A:$A,TODAY()) | C30: =SUMIFS('Sales Log'!$F:$F,'Sales Log'!$A:$A,">="&TODAY()-WEEKDAY(TODAY(),2)+1,'Sales Log'!$A:$A,"<="&TODAY()) | D30: =SUMPRODUCT('Inventory Master'!$J$3:$J$300,'Inventory Master'!$D$3:$D$300) | E30: =COUNTIF('Inventory Master'!$L$3:$L$300,"REORDER") | F30: =SUMIFS('Daily Stock Count'!$I:$I,'Daily Stock Count'!$A:$A,TODAY()) | G30: =SUMPRODUCT('Sales Log'!$D$3:$D$2000,IFNA(VLOOKUP('Sales Log'!$C$3:$C$2000,'Inventory Master'!$A$3:$E$300,5,FALSE)-VLOOKUP('Sales Log'!$C$3:$C$2000,'Inventory Master'!$A$3:$E$300,4,FALSE),0)) | H30: =COUNTIFS('Sales Log'!$A:$A,TODAY()) | I30: =SUMPRODUCT(('Inventory Master'!$L$3:$L$300="REORDER")*('Inventory Master'!$K$3:$K$300-'Inventory Master'!$J$3:$J$300)*'Inventory Master'!$D$3:$D$300)

Sheet Inventory Master
A1: Inventory Master
A2: Item Name | B2: Category | C2: Unit | D2: Cost Price | E2: Sell Price | F2: Opening Stock | G2: Purchases | H2: Sales | I2: Wastage | J2: Current Stock | K2: Reorder Level | L2: Status
G3: =SUMIFS(Purchases!$D:$D,Purchases!$C:$C,$A3) | H3: =SUMIFS('Sales Log'!$D:$D,'Sales Log'!$C:$C,$A3) | I3: =SUMIFS('Daily Stock Count'!$F:$F,'Daily Stock Count'!$B:$B,$A3) | J3: =F3+G3-H3-I3 | L3: =IF(J3<=K3,"REORDER","OK")
G4: =SUMIFS(Purchases!$D:$D,Purchases!$C:$C,$A4) | H4: =SUMIFS('Sales Log'!$D:$D,'Sales Log'!$C:$C,$A4) | I4: =SUMIFS('Daily Stock Count'!$F:$F,'Daily Stock Count'!$B:$B,$A4) | J4: =F4+G4-H4-I4 | L4: =IF(J4<=K4,"REORDER","OK")
G5: =SUMIFS(Purchases!$D:$D,Purchases!$C:$C,$A5) | H5: =SUMIFS('Sales Log'!$D:$D,'Sales Log'!$C:$C,$A5) | I5: =SUMIFS('Daily Stock Count'!$F:$F,'Daily Stock Count'!$B:$B,$A5) | J5: =F5+G5-H5-I5 | L5: =IF(J5<=K5,"REORDER","OK")
G6: =SUMIFS(Purchases!$D:$D,Purchases!$C:$C,$A6) | H6: =SUMIFS('Sales Log'!$D:$D,'Sales Log'!$C:$C,$A6) | I6: =SUMIFS('Daily Stock Count'!$F:$F,'Daily Stock Count'!$B:$B,$A6) | J6: =F6+G6-H6-I6 | L6: =IF(J6<=K6,"REORDER","OK")
G7: =SUMIFS(Purchases!$D:$D,Purchases!$C:$C,$A7) | H7: =SUMIFS('Sales Log'!$D:$D,'Sales Log'!$C:$C,$A7) | I7: =SUMIFS('Daily Stock Count'!$F:$F,'Daily Stock Count'!$B:$B,$A7) | J7: =F7+G7-H7-I7 | L7: =IF(J7<=K7,"REORDER","OK")
G8: =SUMIFS(Purchases!$D:$D,Purchases!$C:$C,$A8) | H8: =SUMIFS('Sales Log'!$D:$D,'Sales Log'!$C:$C,$A8) | I8: =SUMIFS('Daily Stock Count'!$F:$F,'Daily Stock Count'!$B:$B,$A8) | J8: =F8+G8-H8-I8 | L8: =IF(J8<=K8,"REORDER","OK")
G9: =SUMIFS(Purchases!$D:$D,Purchases!$C:$C,$A9) | H9: =SUMIFS('Sales Log'!$D:$D,'Sales Log'!$C:$C,$A9) | I9: =SUMIFS('Daily Stock Count'!$F:$F,'Daily Stock Count'!$B:$B,$A9) | J9: =F9+G9-H9-I9 | L9: =IF(J9<=K9,"REORDER","OK")
G10: =SUMIFS(Purchases!$D:$D,Purchases!$C:$C,$A10) | H10: =SUMIFS('Sales Log'!$D:$D,'Sales Log'!$C:$C,$A10) | I10: =SUMIFS('Daily Stock Count'!$F:$F,'Daily Stock Count'!$B:$B,$A10) | J10: =F10+G10-H10-I10 | L10: =IF(J10<=K10,"REORDER","OK")
G11: =SUMIFS(Purchases!$D:$D,Purchases!$C:$C,$A11) | H11: =SUMIFS('Sales Log'!$D:$D,'Sales Log'!$C:$C,$A11) | I11: =SUMIFS('Daily Stock Count'!$F:$F,'Daily Stock Count'!$B:$B,$A11) | J11: =F11+G11-H11-I11 | L11: =IF(J11<=K11,"REORDER","OK")
G12: =SUMIFS(Purchases!$D:$D,Purchases!$C:$C,$A12) | H12: =SUMIFS('Sales Log'!$D:$D,'Sales Log'!$C:$C,$A12) | I12: =SUMIFS('Daily Stock Count'!$F:$F,'Daily Stock Count'!$B:$B,$A12) | J12: =F12+G12-H12-I12 | L12: =IF(J12<=K12,"REORDER","OK")
G13: =SUMIFS(Purchases!$D:$D,Purchases!$C:$C,$A13) | H13: =SUMIFS('Sales Log'!$D:$D,'Sales Log'!$C:$C,$A13) | I13: =SUMIFS('Daily Stock Count'!$F:$F,'Daily Stock Count'!$B:$B,$A13) | J13: =F13+G13-H13-I13 | L13: =IF(J13<=K13,"REORDER","OK")
G14: =SUMIFS(Purchases!$D:$D,Purchases!$C:$C,$A14) | H14: =SUMIFS('Sales Log'!$D:$D,'Sales Log'!$C:$C,$A14) | I14: =SUMIFS('Daily Stock Count'!$F:$F,'Daily Stock Count'!$B:$B,$A14) | J14: =F14+G14-H14-I14 | L14: =IF(J14<=K14,"REORDER","OK")
... G300: =SUMIFS(Purchases!$D:$D,Purchases!$C:$C,$A300) | H300: =SUMIFS('Sales Log'!$D:$D,'Sales Log'!$C:$C,$A300) | I300: =SUMIFS('Daily Stock Count'!$F:$F,'Daily Stock Count'!$B:$B,$A300) | J300: =F300+G300-H300-I300 | L300: =IF(J300<=K300,"REORDER","OK")

Sheet Daily Stock Count
A1: Daily Stock Count
A2: Date | B2: Item | C2: Opening | D2: Added | E2: Sold | F2: Wastage | G2: Closing Physical Count | H2: Expected Closing | I2: Variance
C3: =IFERROR(VLOOKUP(B3,'Inventory Master'!$A$3:$L$300,6,FALSE),0) | D3: =SUMIFS(Purchases!$D:$D,Purchases!$A:$A,$A3,Purchases!$C:$C,$B3) | E3: =SUMIFS('Sales Log'!$D:$D,'Sales Log'!$A:$A,$A3,'Sales Log'!$C:$C,$B3) | H3: =C3+D3-E3-F3 | I3: =H3-G3
C4: =IFERROR(LOOKUP(2,1/(($B$3:$B3=B4)*($A$3:$A3<A4)),$G$3:$G3),IFERROR(VLOOKUP(B4,'Inventory Master'!$A$3:$L$300,6,FALSE),0)) | D4: =SUMIFS(Purchases!$D:$D,Purchases!$A:$A,$A4,Purchases!$C:$C,$B4) | E4: =SUMIFS('Sales Log'!$D:$D,'Sales Log'!$A:$A,$A4,'Sales Log'!$C:$C,$B4) | H4: =C4+D4-E4-F4 | I4: =H4-G4
C5: =IFERROR(LOOKUP(2,1/(($B$3:$B4=B5)*($A$3:$A4<A5)),$G$3:$G4),IFERROR(VLOOKUP(B5,'Inventory Master'!$A$3:$L$300,6,FALSE),0)) | D5: =SUMIFS(Purchases!$D:$D,Purchases!$A:$A,$A5,Purchases!$C:$C,$B5) | E5: =SUMIFS('Sales Log'!$D:$D,'Sales Log'!$A:$A,$A5,'Sales Log'!$C:$C,$B5) | H5: =C5+D5-E5-F5 | I5: =H5-G5
C6: =IFERROR(LOOKUP(2,1/(($B$3:$B5=B6)*($A$3:$A5<A6)),$G$3:$G5),IFERROR(VLOOKUP(B6,'Inventory Master'!$A$3:$L$300,6,FALSE),0)) | D6: =SUMIFS(Purchases!$D:$D,Purchases!$A:$A,$A6,Purchases!$C:$C,$B6) | E6: =SUMIFS('Sales Log'!$D:$D,'Sales Log'!$A:$A,$A6,'Sales Log'!$C:$C,$B6) | H6: =C6+D6-E6-F6 | I6: =H6-G6
C7: =IFERROR(LOOKUP(2,1/(($B$3:$B6=B7)*($A$3:$A6<A7)),$G$3:$G6),IFERROR(VLOOKUP(B7,'Inventory Master'!$A$3:$L$300,6,FALSE),0)) | D7: =SUMIFS(Purchases!$D:$D,Purchases!$A:$A,$A7,Purchases!$C:$C,$B7) | E7: =SUMIFS('Sales Log'!$D:$D,'Sales Log'!$A:$A,$A7,'Sales Log'!$C:$C,$B7) | H7: =C7+D7-E7-F7 | I7: =H7-G7
C8: =IFERROR(LOOKUP(2,1/(($B$3:$B7=B8)*($A$3:$A7<A8)),$G$3:$G7),IFERROR(VLOOKUP(B8,'Inventory Master'!$A$3:$L$300,6,FALSE),0)) | D8: =SUMIFS(Purchases!$D:$D,Purchases!$A:$A,$A8,Purchases!$C:$C,$B8) | E8: =SUMIFS('Sales Log'!$D:$D,'Sales Log'!$A:$A,$A8,'Sales Log'!$C:$C,$B8) | H8: =C8+D8-E8-F8 | I8: =H8-G8
C9: =IFERROR(LOOKUP(2,1/(($B$3:$B8=B9)*($A$3:$A8<A9)),$G$3:$G8),IFERROR(VLOOKUP(B9,'Inventory Master'!$A$3:$L$300,6,FALSE),0)) | D9: =SUMIFS(Purchases!$D:$D,Purchases!$A:$A,$A9,Purchases!$C:$C,$B9) | E9: =SUMIFS('Sales Log'!$D:$D,'Sales Log'!$A:$A,$A9,'Sales Log'!$C:$C,$B9) | H9: =C9+D9-E9-F9 | I9: =H9-G9
C10: =IFERROR(LOOKUP(2,1/(($B$3:$B9=B10)*($A$3:$A9<A10)),$G$3:$G9),IFERROR(VLOOKUP(B10,'Inventory Master'!$A$3:$L$300,6,FALSE),0)) | D10: =SUMIFS(Purchases!$D:$D,Purchases!$A:$A,$A10,Purchases!$C:$C,$B10) | E10: =SUMIFS('Sales Log'!$D:$D,'Sales Log'!$A:$A,$A10,'Sales Log'!$C:$C,$B10) | H10: =C10+D10-E10-F10 | I10: =H10-G10
C11: =IFERROR(LOOKUP(2,1/(($B$3:$B10=B11)*($A$3:$A10<A11)),$G$3:$G10),IFERROR(VLOOKUP(B11,'Inventory Master'!$A$3:$L$300,6,FALSE),0)) | D11: =SUMIFS(Purchases!$D:$D,Purchases!$A:$A,$A11,Purchases!$C:$C,$B11) | E11: =SUMIFS('Sales Log'!$D:$D,'Sales Log'!$A:$A,$A11,'Sales Log'!$C:$C,$B11) | H11: =C11+D11-E11-F11 | I11: =H11-G11
C12: =IFERROR(LOOKUP(2,1/(($B$3:$B11=B12)*($A$3:$A11<A12)),$G$3:$G11),IFERROR(VLOOKUP(B12,'Inventory Master'!$A$3:$L$300,6,FALSE),0)) | D12: =SUMIFS(Purchases!$D:$D,Purchases!$A:$A,$A12,Purchases!$C:$C,$B12) | E12: =SUMIFS('Sales Log'!$D:$D,'Sales Log'!$A:$A,$A12,'Sales Log'!$C:$C,$B12) | H12: =C12+D12-E12-F12 | I12: =H12-G12
C13: =IFERROR(LOOKUP(2,1/(($B$3:$B12=B13)*($A$3:$A12<A13)),$G$3:$G12),IFERROR(VLOOKUP(B13,'Inventory Master'!$A$3:$L$300,6,FALSE),0)) | D13: =SUMIFS(Purchases!$D:$D,Purchases!$A:$A,$A13,Purchases!$C:$C,$B13) | E13: =SUMIFS('Sales Log'!$D:$D,'Sales Log'!$A:$A,$A13,'Sales Log'!$C:$C,$B13) | H13: =C13+D13-E13-F13 | I13: =H13-G13
C14: =IFERROR(LOOKUP(2,1/(($B$3:$B13=B14)*($A$3:$A13<A14)),$G$3:$G13),IFERROR(VLOOKUP(B14,'Inventory Master'!$A$3:$L$300,6,FALSE),0)) | D14: =SUMIFS(Purchases!$D:$D,Purchases!$A:$A,$A14,Purchases!$C:$C,$B14) | E14: =SUMIFS('Sales Log'!$D:$D,'Sales Log'!$A:$A,$A14,'Sales Log'!$C:$C,$B14) | H14: =C14+D14-E14-F14 | I14: =H14-G14
C15: =IFERROR(LOOKUP(2,1/(($B$3:$B14=B15)*($A$3:$A14<A15)),$G$3:$G14),IFERROR(VLOOKUP(B15,'Inventory Master'!$A$3:$L$300,6,FALSE),0)) | D15: =SUMIFS(Purchases!$D:$D,Purchases!$A:$A,$A15,Purchases!$C:$C,$B15) | E15: =SUMIFS('Sales Log'!$D:$D,'Sales Log'!$A:$A,$A15,'Sales Log'!$C:$C,$B15) | H15: =C15+D15-E15-F15 | I15: =H15-G15
... C1000: =IFERROR(LOOKUP(2,1/(($B$3:$B999=B1000)*($A$3:$A999<A1000)),$G$3:$G999),IFERROR(VLOOKUP(B1000,'Inventory Master'!$A$3:$L$300,6,FALSE),0)) | D1000: =SUMIFS(Purchases!$D:$D,Purchases!$A:$A,$A1000,Purchases!$C:$C,$B1000) | E1000: =SUMIFS('Sales Log'!$D:$D,'Sales Log'!$A:$A,$A1000,'Sales Log'!$C:$C,$B1000) | H1000: =C1000+D1000-E1000-F1000 | I1000: =H1000-G1000

Sheet Sales Log
A1: Sales Log
A2: Date | B2: Waiter | C2: Item | D2: Qty | E2: Unit Price | F2: Total | G2: Payment Method
E3: =IFERROR(VLOOKUP(C3,'Inventory Master'!$A$3:$L$300,5,FALSE),0) | F3: =D3*E3
E4: =IFERROR(VLOOKUP(C4,'Inventory Master'!$A$3:$L$300,5,FALSE),0) | F4: =D4*E4
E5: =IFERROR(VLOOKUP(C5,'Inventory Master'!$A$3:$L$300,5,FALSE),0) | F5: =D5*E5
E6: =IFERROR(VLOOKUP(C6,'Inventory Master'!$A$3:$L$300,5,FALSE),0) | F6: =D6*E6
E7: =IFERROR(VLOOKUP(C7,'Inventory Master'!$A$3:$L$300,5,FALSE),0) | F7: =D7*E7
E8: =IFERROR(VLOOKUP(C8,'Inventory Master'!$A$3:$L$300,5,FALSE),0) | F8: =D8*E8
E9: =IFERROR(VLOOKUP(C9,'Inventory Master'!$A$3:$L$300,5,FALSE),0) | F9: =D9*E9
E10: =IFERROR(VLOOKUP(C10,'Inventory Master'!$A$3:$L$300,5,FALSE),0) | F10: =D10*E10
E11: =IFERROR(VLOOKUP(C11,'Inventory Master'!$A$3:$L$300,5,FALSE),0) | F11: =D11*E11
E12: =IFERROR(VLOOKUP(C12,'Inventory Master'!$A$3:$L$300,5,FALSE),0) | F12: =D12*E12
E13: =IFERROR(VLOOKUP(C13,'Inventory Master'!$A$3:$L$300,5,FALSE),0) | F13: =D13*E13
E14: =IFERROR(VLOOKUP(C14,'Inventory Master'!$A$3:$L$300,5,FALSE),0) | F14: =D14*E14
... E2000: =IFERROR(VLOOKUP(C2000,'Inventory Master'!$A$3:$L$300,5,FALSE),0) | F2000: =D2000*E2000

Sheet Purchases
A1: Purchases
A2: Date | B2: Supplier | C2: Item | D2: Qty | E2: Unit Cost | F2: Total Cost
E3: =IFERROR(VLOOKUP(C3,'Inventory Master'!$A$3:$L$300,4,FALSE),0) | F3: =D3*E3
E4: =IFERROR(VLOOKUP(C4,'Inventory Master'!$A$3:$L$300,4,FALSE),0) | F4: =D4*E4
E5: =IFERROR(VLOOKUP(C5,'Inventory Master'!$A$3:$L$300,4,FALSE),0) | F5: =D5*E5
E6: =IFERROR(VLOOKUP(C6,'Inventory Master'!$A$3:$L$300,4,FALSE),0) | F6: =D6*E6
E7: =IFERROR(VLOOKUP(C7,'Inventory Master'!$A$3:$L$300,4,FALSE),0) | F7: =D7*E7
E8: =IFERROR(VLOOKUP(C8,'Inventory Master'!$A$3:$L$300,4,FALSE),0) | F8: =D8*E8
E9: =IFERROR(VLOOKUP(C9,'Inventory Master'!$A$3:$L$300,4,FALSE),0) | F9: =D9*E9
E10: =IFERROR(VLOOKUP(C10,'Inventory Master'!$A$3:$L$300,4,FALSE),0) | F10: =D10*E10
E11: =IFERROR(VLOOKUP(C11,'Inventory Master'!$A$3:$L$300,4,FALSE),0) | F11: =D11*E11
E12: =IFERROR(VLOOKUP(C12,'Inventory Master'!$A$3:$L$300,4,FALSE),0) | F12: =D12*E12
E13: =IFERROR(VLOOKUP(C13,'Inventory Master'!$A$3:$L$300,4,FALSE),0) | F13: =D13*E13
E14: =IFERROR(VLOOKUP(C14,'Inventory Master'!$A$3:$L$300,4,FALSE),0) | F14: =D14*E14
... E1500: =IFERROR(VLOOKUP(C1500,'Inventory Master'!$A$3:$L$300,4,FALSE),0) | F1500: =D1500*E1500

Sheet Reports
A1: Reports
A3: Daily Sales Summary | E3: Weekly Sales Summary
A4: =QUERY({'Sales Log'!A3:A2000,'Sales Log'!F3:F2000},"select Col1,sum(Col2) where Col1 is not null group by Col1 order by Col1 desc label Col1 'Date', sum(Col2) 'Sales Total'",0) | E4: =QUERY({ARRAYFORMULA('Sales Log'!A3:A2000-WEEKDAY('Sales Log'!A3:A2000,2)+1),'Sales Log'!F3:F2000},"select Col1,sum(Col2) where Col1 is not null group by Col1 order by Col1 desc label Col1 'Week Starting', sum(Col2) 'Sales Total'",0)
A20: Monthly Sales Summary | E20: Variance Summary
A21: =QUERY({TEXT('Sales Log'!A3:A2000,"YYYY-MM"),'Sales Log'!F3:F2000},"select Col1,sum(Col2) where Col1 is not null group by Col1 order by Col1 desc label Col1 'Month', sum(Col2) 'Sales Total'",0) | E21: =QUERY({'Daily Stock Count'!A3:A1000,'Daily Stock Count'!B3:B1000,'Daily Stock Count'!I3:I1000},"select Col1,Col2,Col3 where Col1 is not null and Col3 <> 0 order by Col1 desc label Col1 'Date', Col2 'Item', Col3 'Variance'",0)
A40: If Google Sheets does not import charts, insert charts from the prepared summary blocks in this tab and Dashboard.

Sheet Lists
A1: Categories | B1: Units | C1: Waiters | D1: Payment Methods | E1: Suppliers
A2: Beer | B2: Bottle | C2: Waiter 1 | D2: Cash | E2: Default Supplier
A3: Wine | B3: Can | C3: Waiter 2 | D3: Mobile Money | E3: Local Beverages
A4: Spirits | B4: Case | C4: Waiter 3 | D4: Card | E4: Fresh Foods
A5: Soft Drink | B5: Litre | C5: Bar 1 | D5: Transfer | E5: House Supplies
A6: Food | B6: ml | C6: Manager | D6: Credit
A7: Mixer | B7: Plate
A8: Cleaning | B8: Pack
A9: Other | B9: Kg
B10: Piece
